{
    "key": "group_6880f16009245",
    "title": "CPT \\\\ Events",
    "fields": [
        {
            "key": "field_6880f1cddaafc",
            "label": "Title",
            "name": "title",
            "aria-label": "",
            "type": "text",
            "instructions": "",
            "required": 0,
            "conditional_logic": 0,
            "wrapper": {
                "width": "",
                "class": "",
                "id": ""
            },
            "default_value": "",
            "maxlength": "",
            "allow_in_bindings": 0,
            "placeholder": "",
            "prepend": "",
            "append": ""
        },
        {
            "key": "field_6880f160daafa",
            "label": "Home Team",
            "name": "home_team",
            "aria-label": "",
            "type": "relationship",
            "instructions": "",
            "required": 0,
            "conditional_logic": 0,
            "wrapper": {
                "width": "",
                "class": "",
                "id": ""
            },
            "post_type": [
                "team"
            ],
            "post_status": "",
            "taxonomy": "",
            "filters": [
                "search",
                "post_type",
                "taxonomy"
            ],
            "return_format": "object",
            "acfe_bidirectional": {
                "acfe_bidirectional_enabled": "0"
            },
            "min": 1,
            "max": 1,
            "allow_in_bindings": 0,
            "elements": "",
            "bidirectional": 0,
            "bidirectional_target": []
        },
        {
            "key": "field_6880f1badaafb",
            "label": "Guest Team",
            "name": "guest_team",
            "aria-label": "",
            "type": "relationship",
            "instructions": "",
            "required": 0,
            "conditional_logic": 0,
            "wrapper": {
                "width": "",
                "class": "",
                "id": ""
            },
            "post_type": [
                "team"
            ],
            "post_status": "",
            "taxonomy": "",
            "filters": [
                "search",
                "post_type",
                "taxonomy"
            ],
            "return_format": "object",
            "acfe_bidirectional": {
                "acfe_bidirectional_enabled": "0"
            },
            "min": "",
            "max": 1,
            "allow_in_bindings": 0,
            "elements": "",
            "bidirectional": 0,
            "bidirectional_target": []
        },
        {
            "key": "field_6880f1e9daafd",
            "label": "Date",
            "name": "date",
            "aria-label": "",
            "type": "date_picker",
            "instructions": "",
            "required": 0,
            "conditional_logic": 0,
            "wrapper": {
                "width": "",
                "class": "",
                "id": ""
            },
            "display_format": "F j, Y",
            "return_format": "F j, Y",
            "first_day": 1,
            "allow_in_bindings": 0
        },
        {
            "key": "field_6880f1fedaafe",
            "label": "Time",
            "name": "time",
            "aria-label": "",
            "type": "time_picker",
            "instructions": "",
            "required": 0,
            "conditional_logic": 0,
            "wrapper": {
                "width": "",
                "class": "",
                "id": ""
            },
            "display_format": "H:i",
            "return_format": "H:i",
            "allow_in_bindings": 0
        },
        {
            "key": "field_6880f22cdaaff",
            "label": "Venue",
            "name": "venue",
            "aria-label": "",
            "type": "text",
            "instructions": "",
            "required": 0,
            "conditional_logic": 0,
            "wrapper": {
                "width": "",
                "class": "",
                "id": ""
            },
            "default_value": "",
            "maxlength": "",
            "allow_in_bindings": 0,
            "placeholder": "",
            "prepend": "",
            "append": ""
        }
    ],
    "location": [
        [
            {
                "param": "post_type",
                "operator": "==",
                "value": "event"
            }
        ]
    ],
    "menu_order": 0,
    "position": "normal",
    "style": "default",
    "label_placement": "left",
    "instruction_placement": "label",
    "hide_on_screen": "",
    "active": true,
    "description": "",
    "show_in_rest": 0,
    "acfe_display_title": "",
    "acfe_autosync": [
        "php",
        "json"
    ],
    "acfe_form": 0,
    "acfe_meta": "",
    "acfe_note": "",
    "modified": 1753281444
}
